sharpcut/__init__.py
SharpCut-0.0.0.dist-info/METADATA
SharpCut-0.0.0.dist-info/WHEEL
SharpCut-0.0.0.dist-info/top_level.txt
SharpCut-0.0.0.dist-info/RECORD
