Metadata-Version: 2.1
Name: SharpCut
Version: 0.0.0
Summary: Coming soon
Author-email: The #Cut Research Group <sharp-cut@kth.se>
